cli.py
octopod_cli/__init__.py
octopod_cli/base_command.py
octopod_cli/utils.py
octopod_cli/config_commands/__init__.py
octopod_cli/config_commands/clear_config_command.py
octopod_cli/config_commands/get_config_command.py
octopod_cli/config_commands/set_config_command.py
octopod_cli/file_commands/__init__.py
octopod_cli/file_commands/delete_file_command.py
octopod_cli/file_commands/download_file_command.py
octopod_cli/file_commands/find_file_command.py
octopod_cli/file_commands/update_file_sample_alias_command.py
octopod_cli/file_commands/upload_file_via_api_command.py
octopod_cli/file_commands/upload_file_via_sftp_command.py
octopod_cli/order_commands/__init__.py
octopod_cli/order_commands/cancel_order_command.py
octopod_cli/order_commands/find_order_command.py
octopod_cli/order_commands/submit_order_command.py
octopod_cli/order_commands/update_order_tags_command.py
octopod_cli/organization_commands/__init__.py
octopod_cli/organization_commands/get_organization_info_command.py
octopod_cli/organization_commands/get_organization_models_command.py
octopod_cli/result_commands/__init__.py
octopod_cli/result_commands/download_result_file_command.py
octopod_cli/result_commands/download_result_json_command.py
octopod_cli/result_commands/list_result_pdf_reports_command.py
octopod_cli/result_commands/list_result_samples_command.py
octopod_cli/tag_commands/__init__.py
octopod_cli/tag_commands/create_tag_command.py
octopod_cli/tag_commands/find_tag_command.py
octopod_cli/tag_commands/list_tags_command.py
octopod_cli/tag_commands/update_tag_command.py
octopod_wrapper/__init__.py
octopod_wrapper/exceptions.py
octopod_wrapper/octopod_client.py
octopod_wrapper/octopod_sftp_client.py
octopod_wrapper/utils.py
octopod_wrapper/api/__init__.py
octopod_wrapper/api/base_api.py
octopod_wrapper/api/file_api.py
octopod_wrapper/api/order_api.py
octopod_wrapper/api/organization_api.py
octopod_wrapper/api/result_api.py
octopod_wrapper/api/tag_api.py
galatea_cli-0.0.1.dist-info/LICENSE
galatea_cli-0.0.1.dist-info/METADATA
galatea_cli-0.0.1.dist-info/WHEEL
galatea_cli-0.0.1.dist-info/entry_points.txt
galatea_cli-0.0.1.dist-info/top_level.txt
galatea_cli-0.0.1.dist-info/RECORD
