Metadata-Version: 2.2
Name: galatea-cli
Version: 0.0.1
Summary: Octopod API client
Home-page: https://galatea.bio
Author: Galatea Bio
Author-email: info@galatea.bio
License: MIT
Classifier: Programming Language :: Python :: 3.10
Classifier: License :: OSI Approved :: MIT License
Classifier: Operating System :: OS Independent
Requires-Python: >=3.10
License-File: LICENSE
Requires-Dist: requests==2.32.3
Requires-Dist: paramiko==3.5.1
Dynamic: author
Dynamic: author-email
Dynamic: classifier
Dynamic: description
Dynamic: description-content-type
Dynamic: home-page
Dynamic: license
Dynamic: requires-dist
Dynamic: requires-python
Dynamic: summary
